httperf/__init__.py
httperf/httperf.py
httperf/main.py
perf/__init__.py
perf/main.py
perf/perf.py
httperf-0.0.1.dist-info/LICENSE
httperf-0.0.1.dist-info/METADATA
httperf-0.0.1.dist-info/WHEEL
httperf-0.0.1.dist-info/top_level.txt
httperf-0.0.1.dist-info/RECORD
