Metadata-Version: 2.1
Name: httperf
Version: 0.0.1
Summary: A lightweight python API testing library
Home-page: https://github.com/luhart/perf
Author: Luke Hartman
Author-email: ljhartman10@gmail.com
License: MIT
Platform: UNKNOWN
Classifier: Programming Language :: Python :: 3
Classifier: License :: OSI Approved :: MIT License
Classifier: Operating System :: OS Independent
Requires-Python: >=3.6
